wyoming_openwakeword/__init__.py
wyoming_openwakeword/__main__.py
wyoming_openwakeword/const.py
wyoming_openwakeword/handler.py
wyoming_openwakeword/openwakeword.py
wyoming_openwakeword/state.py
wyoming_openwakeword/models/alexa_v0.1.tflite
wyoming_openwakeword/models/embedding_model.tflite
wyoming_openwakeword/models/hey_jarvis_v0.1.tflite
wyoming_openwakeword/models/hey_mycroft_v0.1.tflite
wyoming_openwakeword/models/hey_rhasspy_v0.1.tflite
wyoming_openwakeword/models/melspectrogram.tflite
wyoming_openwakeword/models/ok_nabu_v0.1.tflite
wyoming_openwakeword-1.8.2.dist-info/LICENSE.md
wyoming_openwakeword-1.8.2.dist-info/METADATA
wyoming_openwakeword-1.8.2.dist-info/WHEEL
wyoming_openwakeword-1.8.2.dist-info/entry_points.txt
wyoming_openwakeword-1.8.2.dist-info/top_level.txt
wyoming_openwakeword-1.8.2.dist-info/RECORD
