Metadata-Version: 2.1
Name: wyoming-openwakeword
Version: 1.8.2
Summary: Wyoming server for openWakeWord
Home-page: http://github.com/rhasspy/wyoming-openwakeword
Author: Michael Hansen
Author-email: mike@rhasspy.org
Keywords: rhasspy wyoming openwakeword
Classifier: Development Status :: 3 - Alpha
Classifier: Intended Audience :: Developers
Classifier: License :: OSI Approved :: Apache Software License
Classifier: Programming Language :: Python :: 3.7
Classifier: Programming Language :: Python :: 3.8
Classifier: Programming Language :: Python :: 3.9
Classifier: Programming Language :: Python :: 3.10
Classifier: Programming Language :: Python :: 3.11
License-File: LICENSE.md
Requires-Dist: tflite-runtime-nightly
Requires-Dist: wyoming ==1.2.0
